sloppy_json/__init__.py
sloppy_json/exceptions.py
sloppy_json/options.py
sloppy_json/parser.py
sloppy_json-0.2.0.dist-info/METADATA
sloppy_json-0.2.0.dist-info/WHEEL
sloppy_json-0.2.0.dist-info/RECORD
