Metadata-Version: 2.4
Name: sloppy-json
Version: 0.2.0
Summary: A forgiving JSON parser that recovers broken JSON from LLM outputs
Author-email: Cemrehan Cavdar <cemrehancavdar@hotmail.com>, Claude <noreply@anthropic.com>
License-Expression: MIT
Keywords: forgiving,json,llm,parser,recovery
Classifier: Development Status :: 3 - Alpha
Classifier: Intended Audience :: Developers
Classifier: License :: OSI Approved :: MIT License
Classifier: Programming Language :: Python :: 3
Classifier: Programming Language :: Python :: 3.12
Classifier: Programming Language :: Python :: 3.13
Classifier: Topic :: Software Development :: Libraries :: Python Modules
Classifier: Topic :: Text Processing :: General
Requires-Python: >=3.12
Provides-Extra: dev
Requires-Dist: basedpyright>=1.20; extra == 'dev'
Requires-Dist: hypothesis>=6.0; extra == 'dev'
Requires-Dist: pytest-cov>=4.0; extra == 'dev'
Requires-Dist: pytest>=8.0; extra == 'dev'
Requires-Dist: ruff>=0.8; extra == 'dev'
Requires-Dist: ty>=0.0.7; extra == 'dev'
